hsproject/__init__.py
hsproject/asgi.py
hsproject/settings.py
hsproject/urls.py
hsproject/wsgi.py
system/__init__.py
system/admin.py
system/apps.py
system/models.py
system/urls.py
system/views.py
system/migrations/__init__.py
hs_add-0.0.0.dist-info/METADATA
hs_add-0.0.0.dist-info/WHEEL
hs_add-0.0.0.dist-info/top_level.txt
hs_add-0.0.0.dist-info/RECORD
