Metadata-Version: 2.1
Name: hs_add
Version: 0.0.0
Summary: hs-add-module
Home-page: 
Author: cjj
Author-email: 
License: MIT
Keywords: hs-add-module
